<?xml version="1.0" encoding="utf-8"?>
<GraphicsSettings>
	<Shadow>
		<SplitCount>3</SplitCount>
		<SplitLambda>0.5</SplitLambda>
		<ShadowMapSizeIndex>1</ShadowMapSizeIndex>
		<OcclusionMapScaleIndex>2</OcclusionMapScaleIndex>
		<OcclusionMapBlurRadius>3</OcclusionMapBlurRadius>
		<OcclusionMapBlurSigma>1</OcclusionMapBlurSigma>
		<DepthBias>0.0001</DepthBias>
	</Shadow>
	<Dof>
		<BlurResolution>2</BlurResolution>
		<BlurRadius>7</BlurRadius>
		<BlurSigma>4</BlurSigma>
	</Dof>
</GraphicsSettings>